plugin_shoebot
