Metadata-Version: 1.0
Name: plugin-shoebot
Version: 0.1.5
Summary: ('Integrate and control shoebot from editors or anything else',)
Home-page: https://github.com/shoebot/plugin-shoebot.git
Author: Stuart Axon
Author-email: stu.axon@gmail.com
License: UNKNOWN
Platform: UNKNOWN
